[
    {
        "DATE": "2020/1/1",
        "city": "xin_jiang",
        "max": "25.833313",
        "min": "9.860113"
    },
    {
        "DATE": "2020/1/2",
        "city": "xin_jiang",
        "max": "21.259195",
        "min": "9.588454"
    },
    {
        "DATE": "2020/1/3",
        "city": "xin_jiang",
        "max": "16.412577",
        "min": "2.6464384"
    },
    {
        "DATE": "2020/1/4",
        "city": "xin_jiang",
        "max": "21.574867",
        "min": "6.1192474"
    },
    {
        "DATE": "2020/1/5",
        "city": "xin_jiang",
        "max": "18.333633",
        "min": "-0.16352057"
    },
    {
        "DATE": "2020/1/6",
        "city": "xin_jiang",
        "max": "11.028412",
        "min": "0.3710407"
    },
    {
        "DATE": "2020/1/7",
        "city": "xin_jiang",
        "max": "21.584106",
        "min": "4.3154573"
    },
    {
        "DATE": "2020/1/8",
        "city": "xin_jiang",
        "max": "16.23471",
        "min": "3.8747284"
    },
    {
        "DATE": "2020/1/9",
        "city": "xin_jiang",
        "max": "22.56806",
        "min": "3.0270922"
    },
    {
        "DATE": "2020/1/10",
        "city": "xin_jiang",
        "max": "15.452866",
        "min": "1.7218441"
    },
    {
        "DATE": "2020/1/11",
        "city": "xin_jiang",
        "max": "23.119204",
        "min": "4.1261845"
    },
    {
        "DATE": "2020/1/12",
        "city": "xin_jiang",
        "max": "12.072662",
        "min": "-1.5195601"
    },
    {
        "DATE": "2020/1/13",
        "city": "xin_jiang",
        "max": "21.084745",
        "min": "6.3468"
    },
    {
        "DATE": "2020/1/14",
        "city": "xin_jiang",
        "max": "25.131653",
        "min": "10.926246"
    },
    {
        "DATE": "2020/1/15",
        "city": "xin_jiang",
        "max": "28.500761",
        "min": "10.186988"
    },
    {
        "DATE": "2020/1/16",
        "city": "xin_jiang",
        "max": "28.098467",
        "min": "10.842664"
    },
    {
        "DATE": "2020/1/17",
        "city": "xin_jiang",
        "max": "20.269735",
        "min": "7.8956337"
    },
    {
        "DATE": "2020/1/18",
        "city": "xin_jiang",
        "max": "26.364809",
        "min": "8.329412"
    },
    {
        "DATE": "2020/1/19",
        "city": "xin_jiang",
        "max": "21.401236",
        "min": "6.487522"
    },
    {
        "DATE": "2020/1/20",
        "city": "xin_jiang",
        "max": "32.639843",
        "min": "11.373397"
    },
    {
        "DATE": "2020/1/21",
        "city": "xin_jiang",
        "max": "27.502228",
        "min": "9.2163515"
    },
    {
        "DATE": "2020/1/22",
        "city": "xin_jiang",
        "max": "26.667149",
        "min": "6.4265194"
    },
    {
        "DATE": "2020/1/23",
        "city": "xin_jiang",
        "max": "25.155535",
        "min": "7.5844593"
    },
    {
        "DATE": "2020/1/24",
        "city": "xin_jiang",
        "max": "34.32784",
        "min": "16.023697"
    },
    {
        "DATE": "2020/1/25",
        "city": "xin_jiang",
        "max": "29.105751",
        "min": "9.923379"
    },
    {
        "DATE": "2020/1/26",
        "city": "xin_jiang",
        "max": "26.158232",
        "min": "6.6233473"
    },
    {
        "DATE": "2020/1/27",
        "city": "xin_jiang",
        "max": "27.526342",
        "min": "9.152682"
    },
    {
        "DATE": "2020/1/28",
        "city": "xin_jiang",
        "max": "32.690693",
        "min": "10.233792"
    },
    {
        "DATE": "2020/1/29",
        "city": "xin_jiang",
        "max": "29.34458",
        "min": "9.925588"
    },
    {
        "DATE": "2020/1/30",
        "city": "xin_jiang",
        "max": "18.884903",
        "min": "0.804587"
    },
    {
        "DATE": "2020/1/31",
        "city": "xin_jiang",
        "max": "18.221643",
        "min": "2.855321"
    },
    {
        "DATE": "2020/2/1",
        "city": "xin_jiang",
        "max": "11.555256",
        "min": "-0.976339"
    },
    {
        "DATE": "2020/2/2",
        "city": "xin_jiang",
        "max": "14.340979",
        "min": "3.374222"
    },
    {
        "DATE": "2020/2/3",
        "city": "xin_jiang",
        "max": "23.711952",
        "min": "2.91465"
    },
    {
        "DATE": "2020/2/4",
        "city": "xin_jiang",
        "max": "22.475895",
        "min": "6.8081"
    },
    {
        "DATE": "2020/2/5",
        "city": "xin_jiang",
        "max": "22.216696",
        "min": "7.0304193"
    },
    {
        "DATE": "2020/2/6",
        "city": "xin_jiang",
        "max": "34.007145",
        "min": "14.043134"
    },
    {
        "DATE": "2020/2/7",
        "city": "xin_jiang",
        "max": "38.15886",
        "min": "16.593855"
    },
    {
        "DATE": "2020/2/8",
        "city": "xin_jiang",
        "max": "46.9983",
        "min": "20.580177"
    },
    {
        "DATE": "2020/2/9",
        "city": "xin_jiang",
        "max": "46.328526",
        "min": "23.581017"
    },
    {
        "DATE": "2020/2/10",
        "city": "xin_jiang",
        "max": "44.582367",
        "min": "19.945108"
    },
    {
        "DATE": "2020/2/11",
        "city": "xin_jiang",
        "max": "35.105553",
        "min": "15.913429"
    },
    {
        "DATE": "2020/2/12",
        "city": "xin_jiang",
        "max": "23.862331",
        "min": "8.330055"
    },
    {
        "DATE": "2020/2/13",
        "city": "xin_jiang",
        "max": "22.061075",
        "min": "8.236159"
    },
    {
        "DATE": "2020/2/14",
        "city": "xin_jiang",
        "max": "27.478777",
        "min": "11.257565"
    },
    {
        "DATE": "2020/2/15",
        "city": "xin_jiang",
        "max": "21.403643",
        "min": "9.627289"
    },
    {
        "DATE": "2020/2/17",
        "city": "xin_jiang",
        "max": "34.437225",
        "min": "12.869826"
    },
    {
        "DATE": "2020/2/18",
        "city": "xin_jiang",
        "max": "30.789892",
        "min": "11.830228"
    },
    {
        "DATE": "2020/2/19",
        "city": "xin_jiang",
        "max": "34.14499",
        "min": "16.81217"
    },
    {
        "DATE": "2020/2/20",
        "city": "xin_jiang",
        "max": "35.67373",
        "min": "14.092028"
    },
    {
        "DATE": "2020/2/21",
        "city": "xin_jiang",
        "max": "29.960964",
        "min": "11.9016905"
    },
    {
        "DATE": "2020/2/22",
        "city": "xin_jiang",
        "max": "34.822834",
        "min": "16.279083"
    },
    {
        "DATE": "2020/2/23",
        "city": "xin_jiang",
        "max": "43.34678",
        "min": "21.268053"
    },
    {
        "DATE": "2020/2/24",
        "city": "xin_jiang",
        "max": "38.726166",
        "min": "18.64288"
    },
    {
        "DATE": "2020/2/25",
        "city": "xin_jiang",
        "max": "36.221573",
        "min": "18.772102"
    },
    {
        "DATE": "2020/2/26",
        "city": "xin_jiang",
        "max": "39.901455",
        "min": "17.952503"
    },
    {
        "DATE": "2020/2/27",
        "city": "xin_jiang",
        "max": "35.097996",
        "min": "13.173071"
    },
    {
        "DATE": "2020/2/28",
        "city": "xin_jiang",
        "max": "39.953888",
        "min": "17.282946"
    },
    {
        "DATE": "2020/2/29",
        "city": "xin_jiang",
        "max": "42.222626",
        "min": "23.794483"
    },
    {
        "DATE": "2020/3/1",
        "city": "xin_jiang",
        "max": "41.064053",
        "min": "23.843113"
    },
    {
        "DATE": "2020/3/2",
        "city": "xin_jiang",
        "max": "38.3368",
        "min": "24.050201"
    },
    {
        "DATE": "2020/3/3",
        "city": "xin_jiang",
        "max": "45.487236",
        "min": "25.029322"
    },
    {
        "DATE": "2020/3/4",
        "city": "xin_jiang",
        "max": "45.40424",
        "min": "27.01785"
    },
    {
        "DATE": "2020/3/5",
        "city": "xin_jiang",
        "max": "42.261227",
        "min": "23.578293"
    },
    {
        "DATE": "2020/3/6",
        "city": "xin_jiang",
        "max": "42.29661",
        "min": "27.660433"
    },
    {
        "DATE": "2020/3/7",
        "city": "xin_jiang",
        "max": "34.48503",
        "min": "17.707489"
    },
    {
        "DATE": "2020/3/8",
        "city": "xin_jiang",
        "max": "25.074888",
        "min": "10.97915"
    },
    {
        "DATE": "2020/3/9",
        "city": "xin_jiang",
        "max": "34.878567",
        "min": "17.703426"
    },
    {
        "DATE": "2020/3/10",
        "city": "xin_jiang",
        "max": "37.15398",
        "min": "19.87482"
    },
    {
        "DATE": "2020/3/11",
        "city": "xin_jiang",
        "max": "47.042282",
        "min": "25.381502"
    },
    {
        "DATE": "2020/3/13",
        "city": "xin_jiang",
        "max": "44.63935",
        "min": "25.7877"
    },
    {
        "DATE": "2020/3/14",
        "city": "xin_jiang",
        "max": "45.541653",
        "min": "29.223215"
    },
    {
        "DATE": "2020/3/15",
        "city": "xin_jiang",
        "max": "50.095356",
        "min": "32.8041"
    },
    {
        "DATE": "2020/3/16",
        "city": "xin_jiang",
        "max": "58.525185",
        "min": "36.167805"
    },
    {
        "DATE": "2020/3/17",
        "city": "xin_jiang",
        "max": "62.768066",
        "min": "38.063107"
    },
    {
        "DATE": "2020/3/18",
        "city": "xin_jiang",
        "max": "61.536995",
        "min": "39.844467"
    },
    {
        "DATE": "2020/3/19",
        "city": "xin_jiang",
        "max": "60.909702",
        "min": "38.80881"
    },
    {
        "DATE": "2020/3/20",
        "city": "xin_jiang",
        "max": "48.559902",
        "min": "28.816147"
    },
    {
        "DATE": "2020/3/21",
        "city": "xin_jiang",
        "max": "54.822407",
        "min": "36.17381"
    },
    {
        "DATE": "2020/3/22",
        "city": "xin_jiang",
        "max": "57.568626",
        "min": "38.23505"
    },
    {
        "DATE": "2020/3/23",
        "city": "xin_jiang",
        "max": "59.595406",
        "min": "33.95544"
    },
    {
        "DATE": "2020/3/24",
        "city": "xin_jiang",
        "max": "44.46218",
        "min": "26.80994"
    },
    {
        "DATE": "2020/3/25",
        "city": "xin_jiang",
        "max": "39.46229",
        "min": "20.833525"
    },
    {
        "DATE": "2020/3/26",
        "city": "xin_jiang",
        "max": "45.04643",
        "min": "28.162401"
    },
    {
        "DATE": "2020/3/27",
        "city": "xin_jiang",
        "max": "47.83654",
        "min": "30.010138"
    },
    {
        "DATE": "2020/3/28",
        "city": "xin_jiang",
        "max": "52.41958",
        "min": "34.46522"
    },
    {
        "DATE": "2020/3/29",
        "city": "xin_jiang",
        "max": "43.148045",
        "min": "27.344692"
    },
    {
        "DATE": "2020/3/30",
        "city": "xin_jiang",
        "max": "46.80616",
        "min": "31.235462"
    },
    {
        "DATE": "2020/3/31",
        "city": "xin_jiang",
        "max": "58.061253",
        "min": "35.98519"
    },
    {
        "DATE": "2020/4/1",
        "city": "xin_jiang",
        "max": "64.89767",
        "min": "40.154755"
    },
    {
        "DATE": "2020/4/2",
        "city": "xin_jiang",
        "max": "59.639473",
        "min": "44.40306"
    },
    {
        "DATE": "2020/4/3",
        "city": "xin_jiang",
        "max": "65.58839",
        "min": "42.81703"
    },
    {
        "DATE": "2020/4/4",
        "city": "xin_jiang",
        "max": "65.34857",
        "min": "42.394535"
    },
    {
        "DATE": "2020/4/5",
        "city": "xin_jiang",
        "max": "66.34562",
        "min": "43.784534"
    },
    {
        "DATE": "2020/4/6",
        "city": "xin_jiang",
        "max": "70.17466",
        "min": "49.3155"
    },
    {
        "DATE": "2020/4/7",
        "city": "xin_jiang",
        "max": "69.56502",
        "min": "46.966297"
    },
    {
        "DATE": "2020/4/8",
        "city": "xin_jiang",
        "max": "72.31486",
        "min": "52.43913"
    },
    {
        "DATE": "2020/4/9",
        "city": "xin_jiang",
        "max": "65.71676",
        "min": "42.01173"
    },
    {
        "DATE": "2020/4/10",
        "city": "xin_jiang",
        "max": "48.79164",
        "min": "37.568027"
    },
    {
        "DATE": "2020/4/11",
        "city": "xin_jiang",
        "max": "58.022614",
        "min": "39.723278"
    },
    {
        "DATE": "2020/4/12",
        "city": "xin_jiang",
        "max": "64.4813",
        "min": "43.13675"
    },
    {
        "DATE": "2020/4/13",
        "city": "xin_jiang",
        "max": "71.30974",
        "min": "49.159214"
    },
    {
        "DATE": "2020/4/14",
        "city": "xin_jiang",
        "max": "65.14746",
        "min": "47.34822"
    },
    {
        "DATE": "2020/4/15",
        "city": "xin_jiang",
        "max": "62.836403",
        "min": "46.282875"
    },
    {
        "DATE": "2020/4/16",
        "city": "xin_jiang",
        "max": "59.537132",
        "min": "41.27935"
    },
    {
        "DATE": "2020/4/17",
        "city": "xin_jiang",
        "max": "59.22641",
        "min": "40.125866"
    },
    {
        "DATE": "2020/4/18",
        "city": "xin_jiang",
        "max": "64.05289",
        "min": "44.336536"
    },
    {
        "DATE": "2020/4/19",
        "city": "xin_jiang",
        "max": "69.84355",
        "min": "47.639374"
    },
    {
        "DATE": "2020/4/20",
        "city": "xin_jiang",
        "max": "68.96814",
        "min": "48.945393"
    },
    {
        "DATE": "2020/4/21",
        "city": "xin_jiang",
        "max": "69.66562",
        "min": "49.42647"
    },
    {
        "DATE": "2020/4/22",
        "city": "xin_jiang",
        "max": "72.76417",
        "min": "51.653347"
    },
    {
        "DATE": "2020/4/23",
        "city": "xin_jiang",
        "max": "83.574715",
        "min": "63.61589"
    },
    {
        "DATE": "2020/4/24",
        "city": "xin_jiang",
        "max": "80.89099",
        "min": "64.17651"
    },
    {
        "DATE": "2020/4/25",
        "city": "xin_jiang",
        "max": "81.41127",
        "min": "64.410995"
    },
    {
        "DATE": "2020/4/26",
        "city": "xin_jiang",
        "max": "85.94891",
        "min": "66.07346"
    },
    {
        "DATE": "2020/4/27",
        "city": "xin_jiang",
        "max": "87.727066",
        "min": "64.74199"
    },
    {
        "DATE": "2020/4/28",
        "city": "xin_jiang",
        "max": "87.40288",
        "min": "62.91802"
    },
    {
        "DATE": "2020/4/29",
        "city": "xin_jiang",
        "max": "87.68952",
        "min": "63.76116"
    },
    {
        "DATE": "2020/4/30",
        "city": "xin_jiang",
        "max": "78.824974",
        "min": "58.787716"
    },
    {
        "DATE": "2020/5/1",
        "city": "xin_jiang",
        "max": "63.07018",
        "min": "45.127567"
    },
    {
        "DATE": "2020/5/2",
        "city": "xin_jiang",
        "max": "72.78199",
        "min": "54.61161"
    },
    {
        "DATE": "2020/5/3",
        "city": "xin_jiang",
        "max": "82.946915",
        "min": "56.719513"
    },
    {
        "DATE": "2020/5/4",
        "city": "xin_jiang",
        "max": "71.273575",
        "min": "49.438637"
    },
    {
        "DATE": "2020/5/5",
        "city": "xin_jiang",
        "max": "66.60677",
        "min": "49.610336"
    },
    {
        "DATE": "2020/5/6",
        "city": "xin_jiang",
        "max": "59.12389",
        "min": "39.63917"
    },
    {
        "DATE": "2020/5/7",
        "city": "xin_jiang",
        "max": "63.01963",
        "min": "46.0188"
    },
    {
        "DATE": "2020/5/8",
        "city": "xin_jiang",
        "max": "71.56386",
        "min": "50.274857"
    },
    {
        "DATE": "2020/5/9",
        "city": "xin_jiang",
        "max": "79.39277",
        "min": "55.871414"
    },
    {
        "DATE": "2020/5/10",
        "city": "xin_jiang",
        "max": "83.532234",
        "min": "61.61103"
    },
    {
        "DATE": "2020/5/11",
        "city": "xin_jiang",
        "max": "85.205795",
        "min": "63.975796"
    },
    {
        "DATE": "2020/5/12",
        "city": "xin_jiang",
        "max": "81.76597",
        "min": "60.834995"
    },
    {
        "DATE": "2020/5/13",
        "city": "xin_jiang",
        "max": "78.92702",
        "min": "57.281796"
    },
    {
        "DATE": "2020/5/14",
        "city": "xin_jiang",
        "max": "81.19537",
        "min": "59.86905"
    },
    {
        "DATE": "2020/5/15",
        "city": "xin_jiang",
        "max": "85.378815",
        "min": "62.154163"
    },
    {
        "DATE": "2020/5/16",
        "city": "xin_jiang",
        "max": "76.34925",
        "min": "58.74691"
    },
    {
        "DATE": "2020/5/17",
        "city": "xin_jiang",
        "max": "78.98822",
        "min": "60.953453"
    },
    {
        "DATE": "2020/5/18",
        "city": "xin_jiang",
        "max": "82.187965",
        "min": "61.260674"
    },
    {
        "DATE": "2020/5/19",
        "city": "xin_jiang",
        "max": "83.1787",
        "min": "62.655132"
    },
    {
        "DATE": "2020/5/20",
        "city": "xin_jiang",
        "max": "75.44714",
        "min": "56.00941"
    },
    {
        "DATE": "2020/5/21",
        "city": "xin_jiang",
        "max": "62.09567",
        "min": "46.725613"
    },
    {
        "DATE": "2020/5/22",
        "city": "xin_jiang",
        "max": "78.2569",
        "min": "57.818516"
    },
    {
        "DATE": "2020/5/23",
        "city": "xin_jiang",
        "max": "81.432396",
        "min": "58.119125"
    },
    {
        "DATE": "2020/5/24",
        "city": "xin_jiang",
        "max": "69.884674",
        "min": "48.334385"
    },
    {
        "DATE": "2020/5/25",
        "city": "xin_jiang",
        "max": "80.52216",
        "min": "59.26939"
    },
    {
        "DATE": "2020/5/26",
        "city": "xin_jiang",
        "max": "83.56464",
        "min": "61.605625"
    },
    {
        "DATE": "2020/5/27",
        "city": "xin_jiang",
        "max": "88.76239",
        "min": "66.3149"
    },
    {
        "DATE": "2020/5/28",
        "city": "xin_jiang",
        "max": "73.57496",
        "min": "55.92094"
    },
    {
        "DATE": "2020/5/29",
        "city": "xin_jiang",
        "max": "79.96292",
        "min": "58.53295"
    },
    {
        "DATE": "2020/5/30",
        "city": "xin_jiang",
        "max": "87.343376",
        "min": "63.84247"
    },
    {
        "DATE": "2020/5/31",
        "city": "xin_jiang",
        "max": "86.01963",
        "min": "64.88496"
    },
    {
        "DATE": "2020/6/1",
        "city": "xin_jiang",
        "max": "87.90656",
        "min": "68.206024"
    },
    {
        "DATE": "2020/6/2",
        "city": "xin_jiang",
        "max": "90.94358",
        "min": "69.863976"
    },
    {
        "DATE": "2020/6/3",
        "city": "xin_jiang",
        "max": "90.06167",
        "min": "69.280876"
    },
    {
        "DATE": "2020/6/4",
        "city": "xin_jiang",
        "max": "88.18421",
        "min": "66.18238"
    },
    {
        "DATE": "2020/6/5",
        "city": "xin_jiang",
        "max": "79.034836",
        "min": "56.490105"
    },
    {
        "DATE": "2020/6/6",
        "city": "xin_jiang",
        "max": "65.587204",
        "min": "51.090347"
    },
    {
        "DATE": "2020/6/7",
        "city": "xin_jiang",
        "max": "67.16806",
        "min": "52.64367"
    },
    {
        "DATE": "2020/6/8",
        "city": "xin_jiang",
        "max": "74.67296",
        "min": "56.439075"
    },
    {
        "DATE": "2020/6/9",
        "city": "xin_jiang",
        "max": "80.30084",
        "min": "61.264503"
    },
    {
        "DATE": "2020/6/10",
        "city": "xin_jiang",
        "max": "79.97858",
        "min": "61.40477"
    },
    {
        "DATE": "2020/6/11",
        "city": "xin_jiang",
        "max": "78.406654",
        "min": "62.51144"
    },
    {
        "DATE": "2020/6/12",
        "city": "xin_jiang",
        "max": "80.828674",
        "min": "62.438286"
    },
    {
        "DATE": "2020/6/13",
        "city": "xin_jiang",
        "max": "84.37497",
        "min": "64.02879"
    },
    {
        "DATE": "2020/6/14",
        "city": "xin_jiang",
        "max": "80.54611",
        "min": "62.535442"
    },
    {
        "DATE": "2020/6/15",
        "city": "xin_jiang",
        "max": "85.92539",
        "min": "65.90771"
    },
    {
        "DATE": "2020/6/16",
        "city": "xin_jiang",
        "max": "90.82947",
        "min": "67.402466"
    },
    {
        "DATE": "2020/6/17",
        "city": "xin_jiang",
        "max": "84.25272",
        "min": "63.299603"
    },
    {
        "DATE": "2020/6/18",
        "city": "xin_jiang",
        "max": "79.73978",
        "min": "59.495705"
    },
    {
        "DATE": "2020/6/19",
        "city": "xin_jiang",
        "max": "72.128586",
        "min": "56.57427"
    },
    {
        "DATE": "2020/6/20",
        "city": "xin_jiang",
        "max": "80.13994",
        "min": "59.170006"
    },
    {
        "DATE": "2020/6/21",
        "city": "xin_jiang",
        "max": "67.441216",
        "min": "52.165527"
    },
    {
        "DATE": "2020/6/22",
        "city": "xin_jiang",
        "max": "74.70275",
        "min": "56.139168"
    },
    {
        "DATE": "2020/6/23",
        "city": "xin_jiang",
        "max": "80.26093",
        "min": "60.969334"
    },
    {
        "DATE": "2020/6/24",
        "city": "xin_jiang",
        "max": "81.07214",
        "min": "60.7868"
    },
    {
        "DATE": "2020/6/25",
        "city": "xin_jiang",
        "max": "84.48943",
        "min": "63.11781"
    },
    {
        "DATE": "2020/6/26",
        "city": "xin_jiang",
        "max": "87.62308",
        "min": "68.716515"
    },
    {
        "DATE": "2020/6/27",
        "city": "xin_jiang",
        "max": "88.834305",
        "min": "68.10071"
    },
    {
        "DATE": "2020/6/28",
        "city": "xin_jiang",
        "max": "72.48913",
        "min": "57.19132"
    },
    {
        "DATE": "2020/6/29",
        "city": "xin_jiang",
        "max": "59.514084",
        "min": "43.70776"
    },
    {
        "DATE": "2020/6/30",
        "city": "xin_jiang",
        "max": "72.32661",
        "min": "55.699123"
    },
    {
        "DATE": "2020/7/1",
        "city": "xin_jiang",
        "max": "94.92452",
        "min": "70.49019"
    },
    {
        "DATE": "2020/7/2",
        "city": "xin_jiang",
        "max": "74.67533",
        "min": "57.29821"
    },
    {
        "DATE": "2020/7/3",
        "city": "xin_jiang",
        "max": "70.535934",
        "min": "52.269115"
    },
    {
        "DATE": "2020/7/4",
        "city": "xin_jiang",
        "max": "78.64274",
        "min": "59.05227"
    },
    {
        "DATE": "2020/7/5",
        "city": "xin_jiang",
        "max": "81.07036",
        "min": "60.5702"
    },
    {
        "DATE": "2020/7/6",
        "city": "xin_jiang",
        "max": "82.57168",
        "min": "62.580116"
    },
    {
        "DATE": "2020/7/7",
        "city": "xin_jiang",
        "max": "83.401276",
        "min": "65.01043"
    },
    {
        "DATE": "2020/7/8",
        "city": "xin_jiang",
        "max": "85.2257",
        "min": "66.80874"
    },
    {
        "DATE": "2020/7/9",
        "city": "xin_jiang",
        "max": "83.74652",
        "min": "63.656338"
    },
    {
        "DATE": "2020/7/10",
        "city": "xin_jiang",
        "max": "86.17902",
        "min": "66.362175"
    },
    {
        "DATE": "2020/7/11",
        "city": "xin_jiang",
        "max": "88.76453",
        "min": "66.30145"
    },
    {
        "DATE": "2020/7/12",
        "city": "xin_jiang",
        "max": "95.551506",
        "min": "70.750885"
    },
    {
        "DATE": "2020/7/13",
        "city": "xin_jiang",
        "max": "99.96303",
        "min": "74.7678"
    },
    {
        "DATE": "2020/7/14",
        "city": "xin_jiang",
        "max": "97.0831",
        "min": "74.70576"
    },
    {
        "DATE": "2020/7/15",
        "city": "xin_jiang",
        "max": "81.932274",
        "min": "60.880054"
    },
    {
        "DATE": "2020/7/16",
        "city": "xin_jiang",
        "max": "74.278755",
        "min": "62.678196"
    },
    {
        "DATE": "2020/7/17",
        "city": "xin_jiang",
        "max": "79.18095",
        "min": "59.420765"
    },
    {
        "DATE": "2020/7/18",
        "city": "xin_jiang",
        "max": "87.793594",
        "min": "66.19974"
    },
    {
        "DATE": "2020/7/19",
        "city": "xin_jiang",
        "max": "90.0627",
        "min": "68.42931"
    },
    {
        "DATE": "2020/7/20",
        "city": "xin_jiang",
        "max": "86.14409",
        "min": "66.28373"
    },
    {
        "DATE": "2020/7/21",
        "city": "xin_jiang",
        "max": "81.37841",
        "min": "61.07899"
    },
    {
        "DATE": "2020/7/22",
        "city": "xin_jiang",
        "max": "84.787544",
        "min": "64.18716"
    },
    {
        "DATE": "2020/7/23",
        "city": "xin_jiang",
        "max": "89.69227",
        "min": "67.36881"
    },
    {
        "DATE": "2020/7/24",
        "city": "xin_jiang",
        "max": "93.105515",
        "min": "75.95086"
    },
    {
        "DATE": "2020/7/25",
        "city": "xin_jiang",
        "max": "89.75859",
        "min": "70.275505"
    },
    {
        "DATE": "2020/7/26",
        "city": "xin_jiang",
        "max": "85.70983",
        "min": "69.18728"
    },
    {
        "DATE": "2020/7/27",
        "city": "xin_jiang",
        "max": "80.12986",
        "min": "59.863564"
    },
    {
        "DATE": "2020/7/28",
        "city": "xin_jiang",
        "max": "85.584274",
        "min": "63.608875"
    },
    {
        "DATE": "2020/7/29",
        "city": "xin_jiang",
        "max": "87.65766",
        "min": "65.32183"
    },
    {
        "DATE": "2020/7/30",
        "city": "xin_jiang",
        "max": "91.26844",
        "min": "70.35781"
    },
    {
        "DATE": "2020/7/31",
        "city": "xin_jiang",
        "max": "89.49152",
        "min": "70.138084"
    },
    {
        "DATE": "2020/8/1",
        "city": "xin_jiang",
        "max": "86.3644",
        "min": "66.817245"
    },
    {
        "DATE": "2020/8/2",
        "city": "xin_jiang",
        "max": "88.52121",
        "min": "68.17307"
    },
    {
        "DATE": "2020/8/3",
        "city": "xin_jiang",
        "max": "88.64435",
        "min": "67.452736"
    },
    {
        "DATE": "2020/8/4",
        "city": "xin_jiang",
        "max": "88.8608",
        "min": "66.609924"
    },
    {
        "DATE": "2020/8/5",
        "city": "xin_jiang",
        "max": "91.52654",
        "min": "70.52082"
    },
    {
        "DATE": "2020/8/6",
        "city": "xin_jiang",
        "max": "86.15982",
        "min": "65.86304"
    },
    {
        "DATE": "2020/8/7",
        "city": "xin_jiang",
        "max": "90.74277",
        "min": "68.80073"
    },
    {
        "DATE": "2020/8/8",
        "city": "xin_jiang",
        "max": "87.5472",
        "min": "66.670296"
    },
    {
        "DATE": "2020/8/9",
        "city": "xin_jiang",
        "max": "75.378105",
        "min": "59.24561"
    },
    {
        "DATE": "2020/8/10",
        "city": "xin_jiang",
        "max": "78.95546",
        "min": "62.90515"
    },
    {
        "DATE": "2020/8/11",
        "city": "xin_jiang",
        "max": "76.32444",
        "min": "56.873756"
    },
    {
        "DATE": "2020/8/12",
        "city": "xin_jiang",
        "max": "77.64319",
        "min": "60.012123"
    },
    {
        "DATE": "2020/8/13",
        "city": "xin_jiang",
        "max": "81.98267",
        "min": "60.519604"
    },
    {
        "DATE": "2020/8/14",
        "city": "xin_jiang",
        "max": "79.88865",
        "min": "62.24181"
    },
    {
        "DATE": "2020/8/15",
        "city": "xin_jiang",
        "max": "86.86779",
        "min": "65.41057"
    },
    {
        "DATE": "2020/8/16",
        "city": "xin_jiang",
        "max": "89.31617",
        "min": "65.28753"
    },
    {
        "DATE": "2020/8/17",
        "city": "xin_jiang",
        "max": "92.06603",
        "min": "73.36322"
    },
    {
        "DATE": "2020/8/18",
        "city": "xin_jiang",
        "max": "90.861725",
        "min": "74.43633"
    },
    {
        "DATE": "2020/8/19",
        "city": "xin_jiang",
        "max": "89.70761",
        "min": "68.6923"
    },
    {
        "DATE": "2020/8/20",
        "city": "xin_jiang",
        "max": "93.32722",
        "min": "70.59345"
    },
    {
        "DATE": "2020/8/21",
        "city": "xin_jiang",
        "max": "87.32956",
        "min": "66.41538"
    },
    {
        "DATE": "2020/8/22",
        "city": "xin_jiang",
        "max": "75.14396",
        "min": "58.48419"
    },
    {
        "DATE": "2020/8/23",
        "city": "xin_jiang",
        "max": "80.92409",
        "min": "61.408604"
    },
    {
        "DATE": "2020/8/24",
        "city": "xin_jiang",
        "max": "87.9693",
        "min": "66.53948"
    },
    {
        "DATE": "2020/8/25",
        "city": "xin_jiang",
        "max": "92.0355",
        "min": "67.707245"
    },
    {
        "DATE": "2020/8/26",
        "city": "xin_jiang",
        "max": "84.01073",
        "min": "64.01477"
    },
    {
        "DATE": "2020/8/27",
        "city": "xin_jiang",
        "max": "71.10953",
        "min": "52.427933"
    },
    {
        "DATE": "2020/8/28",
        "city": "xin_jiang",
        "max": "59.20597",
        "min": "51.0004"
    },
    {
        "DATE": "2020/8/29",
        "city": "xin_jiang",
        "max": "59.78275",
        "min": "51.32784"
    },
    {
        "DATE": "2020/8/30",
        "city": "xin_jiang",
        "max": "64.30522",
        "min": "50.139122"
    },
    {
        "DATE": "2020/8/31",
        "city": "xin_jiang",
        "max": "64.38455",
        "min": "51.266747"
    },
    {
        "DATE": "2020/9/1",
        "city": "xin_jiang",
        "max": "66.692276",
        "min": "49.355896"
    },
    {
        "DATE": "2020/9/2",
        "city": "xin_jiang",
        "max": "73.770325",
        "min": "51.868195"
    },
    {
        "DATE": "2020/9/3",
        "city": "xin_jiang",
        "max": "78.81452",
        "min": "54.603065"
    },
    {
        "DATE": "2020/9/4",
        "city": "xin_jiang",
        "max": "79.968315",
        "min": "57.381153"
    },
    {
        "DATE": "2020/9/5",
        "city": "xin_jiang",
        "max": "81.37839",
        "min": "59.63089"
    },
    {
        "DATE": "2020/9/6",
        "city": "xin_jiang",
        "max": "81.19863",
        "min": "58.804977"
    },
    {
        "DATE": "2020/9/7",
        "city": "xin_jiang",
        "max": "79.533745",
        "min": "56.8979"
    },
    {
        "DATE": "2020/9/8",
        "city": "xin_jiang",
        "max": "80.160576",
        "min": "57.10203"
    },
    {
        "DATE": "2020/9/9",
        "city": "xin_jiang",
        "max": "80.976326",
        "min": "59.269287"
    },
    {
        "DATE": "2020/9/10",
        "city": "xin_jiang",
        "max": "81.88227",
        "min": "60.408043"
    },
    {
        "DATE": "2020/9/11",
        "city": "xin_jiang",
        "max": "77.08573",
        "min": "57.650566"
    },
    {
        "DATE": "2020/9/12",
        "city": "xin_jiang",
        "max": "74.38217",
        "min": "54.540474"
    },
    {
        "DATE": "2020/9/13",
        "city": "xin_jiang",
        "max": "71.63442",
        "min": "53.44649"
    },
    {
        "DATE": "2020/9/14",
        "city": "xin_jiang",
        "max": "70.44173",
        "min": "50.9895"
    },
    {
        "DATE": "2020/9/15",
        "city": "xin_jiang",
        "max": "70.48077",
        "min": "50.549667"
    },
    {
        "DATE": "2020/9/16",
        "city": "xin_jiang",
        "max": "73.150444",
        "min": "50.344566"
    },
    {
        "DATE": "2020/9/17",
        "city": "xin_jiang",
        "max": "71.52715",
        "min": "55.335506"
    },
    {
        "DATE": "2020/9/18",
        "city": "xin_jiang",
        "max": "69.60901",
        "min": "52.20566"
    },
    {
        "DATE": "2020/9/19",
        "city": "xin_jiang",
        "max": "72.616684",
        "min": "52.093685"
    },
    {
        "DATE": "2020/9/20",
        "city": "xin_jiang",
        "max": "75.12512",
        "min": "51.402054"
    },
    {
        "DATE": "2020/9/21",
        "city": "xin_jiang",
        "max": "77.0074",
        "min": "53.943367"
    },
    {
        "DATE": "2020/9/22",
        "city": "xin_jiang",
        "max": "70.573235",
        "min": "47.819946"
    },
    {
        "DATE": "2020/9/23",
        "city": "xin_jiang",
        "max": "66.74114",
        "min": "48.76143"
    },
    {
        "DATE": "2020/9/24",
        "city": "xin_jiang",
        "max": "70.33503",
        "min": "49.064808"
    },
    {
        "DATE": "2020/9/25",
        "city": "xin_jiang",
        "max": "64.178566",
        "min": "51.851192"
    },
    {
        "DATE": "2020/9/26",
        "city": "xin_jiang",
        "max": "60.508068",
        "min": "44.739956"
    },
    {
        "DATE": "2020/9/27",
        "city": "xin_jiang",
        "max": "62.36314",
        "min": "42.54521"
    },
    {
        "DATE": "2020/9/28",
        "city": "xin_jiang",
        "max": "64.44795",
        "min": "45.9186"
    },
    {
        "DATE": "2020/9/29",
        "city": "xin_jiang",
        "max": "68.284485",
        "min": "48.577507"
    },
    {
        "DATE": "2020/9/30",
        "city": "xin_jiang",
        "max": "62.705563",
        "min": "48.267338"
    },
    {
        "DATE": "2020/10/1",
        "city": "xin_jiang",
        "max": "64.73544",
        "min": "45.269398"
    },
    {
        "DATE": "2020/10/2",
        "city": "xin_jiang",
        "max": "70.04508",
        "min": "48.18173"
    },
    {
        "DATE": "2020/10/3",
        "city": "xin_jiang",
        "max": "75.82442",
        "min": "53.04888"
    },
    {
        "DATE": "2020/10/4",
        "city": "xin_jiang",
        "max": "76.074936",
        "min": "58.03193"
    },
    {
        "DATE": "2020/10/5",
        "city": "xin_jiang",
        "max": "79.21243",
        "min": "57.775696"
    },
    {
        "DATE": "2020/10/6",
        "city": "xin_jiang",
        "max": "64.58729",
        "min": "49.953213"
    },
    {
        "DATE": "2020/10/7",
        "city": "xin_jiang",
        "max": "61.304123",
        "min": "47.064903"
    },
    {
        "DATE": "2020/10/8",
        "city": "xin_jiang",
        "max": "61.840816",
        "min": "44.397392"
    },
    {
        "DATE": "2020/10/9",
        "city": "xin_jiang",
        "max": "56.31722",
        "min": "38.262257"
    },
    {
        "DATE": "2020/10/10",
        "city": "xin_jiang",
        "max": "52.314175",
        "min": "37.95839"
    },
    {
        "DATE": "2020/10/11",
        "city": "xin_jiang",
        "max": "49.209625",
        "min": "37.709827"
    },
    {
        "DATE": "2020/10/12",
        "city": "xin_jiang",
        "max": "56.58457",
        "min": "38.34094"
    },
    {
        "DATE": "2020/10/13",
        "city": "xin_jiang",
        "max": "58.024162",
        "min": "39.888344"
    },
    {
        "DATE": "2020/10/14",
        "city": "xin_jiang",
        "max": "58.86649",
        "min": "39.68428"
    },
    {
        "DATE": "2020/10/15",
        "city": "xin_jiang",
        "max": "60.224922",
        "min": "40.95479"
    },
    {
        "DATE": "2020/10/16",
        "city": "xin_jiang",
        "max": "62.82885",
        "min": "42.121952"
    },
    {
        "DATE": "2020/10/17",
        "city": "xin_jiang",
        "max": "68.46642",
        "min": "44.98365"
    },
    {
        "DATE": "2020/10/18",
        "city": "xin_jiang",
        "max": "68.686806",
        "min": "46.625362"
    },
    {
        "DATE": "2020/10/19",
        "city": "xin_jiang",
        "max": "66.95077",
        "min": "46.235497"
    },
    {
        "DATE": "2020/10/20",
        "city": "xin_jiang",
        "max": "54.684986",
        "min": "39.12081"
    },
    {
        "DATE": "2020/10/21",
        "city": "xin_jiang",
        "max": "47.738537",
        "min": "37.05465"
    },
    {
        "DATE": "2020/10/22",
        "city": "xin_jiang",
        "max": "46.804146",
        "min": "29.479933"
    },
    {
        "DATE": "2020/10/23",
        "city": "xin_jiang",
        "max": "47.38066",
        "min": "28.946165"
    },
    {
        "DATE": "2020/10/24",
        "city": "xin_jiang",
        "max": "49.31643",
        "min": "33.851135"
    },
    {
        "DATE": "2020/10/25",
        "city": "xin_jiang",
        "max": "50.555714",
        "min": "36.23519"
    },
    {
        "DATE": "2020/10/26",
        "city": "xin_jiang",
        "max": "52.5468",
        "min": "36.406273"
    },
    {
        "DATE": "2020/10/27",
        "city": "xin_jiang",
        "max": "58.544563",
        "min": "39.7491"
    },
    {
        "DATE": "2020/10/28",
        "city": "xin_jiang",
        "max": "52.593014",
        "min": "37.646126"
    },
    {
        "DATE": "2020/10/29",
        "city": "xin_jiang",
        "max": "41.294914",
        "min": "30.450253"
    },
    {
        "DATE": "2020/10/30",
        "city": "xin_jiang",
        "max": "34.759754",
        "min": "24.716055"
    },
    {
        "DATE": "2020/10/31",
        "city": "xin_jiang",
        "max": "38.32479",
        "min": "25.091162"
    },
    {
        "DATE": "2020/11/1",
        "city": "xin_jiang",
        "max": "35.316116",
        "min": "23.519444"
    },
    {
        "DATE": "2020/11/2",
        "city": "xin_jiang",
        "max": "38.196934",
        "min": "25.665798"
    },
    {
        "DATE": "2020/11/3",
        "city": "xin_jiang",
        "max": "40.280655",
        "min": "23.607414"
    },
    {
        "DATE": "2020/11/4",
        "city": "xin_jiang",
        "max": "39.251442",
        "min": "27.971544"
    },
    {
        "DATE": "2020/11/5",
        "city": "xin_jiang",
        "max": "39.98743",
        "min": "26.777313"
    },
    {
        "DATE": "2020/11/6",
        "city": "xin_jiang",
        "max": "42.92408",
        "min": "28.623941"
    },
    {
        "DATE": "2020/11/7",
        "city": "xin_jiang",
        "max": "58.2984",
        "min": "38.16164"
    },
    {
        "DATE": "2020/11/8",
        "city": "xin_jiang",
        "max": "54.868958",
        "min": "37.893234"
    },
    {
        "DATE": "2020/11/9",
        "city": "xin_jiang",
        "max": "39.6138",
        "min": "27.766153"
    },
    {
        "DATE": "2020/11/10",
        "city": "xin_jiang",
        "max": "31.255629",
        "min": "22.84315"
    },
    {
        "DATE": "2020/11/11",
        "city": "xin_jiang",
        "max": "34.96714",
        "min": "20.523005"
    },
    {
        "DATE": "2020/11/12",
        "city": "xin_jiang",
        "max": "37.68178",
        "min": "21.967205"
    },
    {
        "DATE": "2020/11/13",
        "city": "xin_jiang",
        "max": "43.850296",
        "min": "24.14565"
    },
    {
        "DATE": "2020/11/14",
        "city": "xin_jiang",
        "max": "44.974",
        "min": "28.65011"
    },
    {
        "DATE": "2020/11/15",
        "city": "xin_jiang",
        "max": "35.99067",
        "min": "24.955338"
    },
    {
        "DATE": "2020/11/16",
        "city": "xin_jiang",
        "max": "34.715782",
        "min": "24.500269"
    },
    {
        "DATE": "2020/11/17",
        "city": "xin_jiang",
        "max": "32.271202",
        "min": "19.763548"
    },
    {
        "DATE": "2020/11/18",
        "city": "xin_jiang",
        "max": "31.731836",
        "min": "16.340624"
    },
    {
        "DATE": "2020/11/19",
        "city": "xin_jiang",
        "max": "31.98106",
        "min": "18.916227"
    },
    {
        "DATE": "2020/11/20",
        "city": "xin_jiang",
        "max": "39.23591",
        "min": "22.858288"
    },
    {
        "DATE": "2020/11/21",
        "city": "xin_jiang",
        "max": "38.069454",
        "min": "24.986433"
    },
    {
        "DATE": "2020/11/22",
        "city": "xin_jiang",
        "max": "34.249973",
        "min": "19.254469"
    },
    {
        "DATE": "2020/11/23",
        "city": "xin_jiang",
        "max": "36.33945",
        "min": "25.134752"
    },
    {
        "DATE": "2020/11/24",
        "city": "xin_jiang",
        "max": "32.81048",
        "min": "23.997677"
    },
    {
        "DATE": "2020/11/25",
        "city": "xin_jiang",
        "max": "35.072968",
        "min": "26.611322"
    },
    {
        "DATE": "2020/11/26",
        "city": "xin_jiang",
        "max": "34.903217",
        "min": "26.395203"
    },
    {
        "DATE": "2020/11/27",
        "city": "xin_jiang",
        "max": "35.11637",
        "min": "26.04108"
    },
    {
        "DATE": "2020/11/28",
        "city": "xin_jiang",
        "max": "35.28774",
        "min": "25.386898"
    },
    {
        "DATE": "2020/11/29",
        "city": "xin_jiang",
        "max": "35.65557",
        "min": "26.918068"
    },
    {
        "DATE": "2020/11/30",
        "city": "xin_jiang",
        "max": "35.95883",
        "min": "27.09524"
    },
    {
        "DATE": "2020/12/1",
        "city": "xin_jiang",
        "max": "30.677334",
        "min": "24.280432"
    },
    {
        "DATE": "2020/12/2",
        "city": "xin_jiang",
        "max": "30.737411",
        "min": "24.662842"
    },
    {
        "DATE": "2020/12/3",
        "city": "xin_jiang",
        "max": "30.266548",
        "min": "21.696863"
    },
    {
        "DATE": "2020/12/4",
        "city": "xin_jiang",
        "max": "32.04633",
        "min": "22.655262"
    },
    {
        "DATE": "2020/12/5",
        "city": "xin_jiang",
        "max": "28.982212",
        "min": "18.636467"
    },
    {
        "DATE": "2020/12/6",
        "city": "xin_jiang",
        "max": "27.656338",
        "min": "14.665795"
    },
    {
        "DATE": "2020/12/7",
        "city": "xin_jiang",
        "max": "23.454184",
        "min": "14.589054"
    },
    {
        "DATE": "2020/12/8",
        "city": "xin_jiang",
        "max": "17.757097",
        "min": "12.72207"
    },
    {
        "DATE": "2020/12/9",
        "city": "xin_jiang",
        "max": "15.338757",
        "min": "4.84626"
    },
    {
        "DATE": "2020/12/10",
        "city": "xin_jiang",
        "max": "22.200275",
        "min": "8.437759"
    },
    {
        "DATE": "2020/12/11",
        "city": "xin_jiang",
        "max": "25.451563",
        "min": "10.859489"
    },
    {
        "DATE": "2020/12/12",
        "city": "xin_jiang",
        "max": "25.862017",
        "min": "10.187308"
    },
    {
        "DATE": "2020/12/13",
        "city": "xin_jiang",
        "max": "28.536228",
        "min": "15.422865"
    },
    {
        "DATE": "2020/12/14",
        "city": "xin_jiang",
        "max": "29.048212",
        "min": "11.713004"
    },
    {
        "DATE": "2020/12/15",
        "city": "xin_jiang",
        "max": "21.970919",
        "min": "9.452051"
    },
    {
        "DATE": "2020/12/16",
        "city": "xin_jiang",
        "max": "25.903522",
        "min": "14.357496"
    },
    {
        "DATE": "2020/12/17",
        "city": "xin_jiang",
        "max": "16.627817",
        "min": "8.230684"
    },
    {
        "DATE": "2020/12/18",
        "city": "xin_jiang",
        "max": "15.324308",
        "min": "6.3465447"
    },
    {
        "DATE": "2020/12/19",
        "city": "xin_jiang",
        "max": "12.315342",
        "min": "5.7338862"
    },
    {
        "DATE": "2020/12/20",
        "city": "xin_jiang",
        "max": "11.499043",
        "min": "6.2966194"
    },
    {
        "DATE": "2020/12/21",
        "city": "xin_jiang",
        "max": "9.530659",
        "min": "0.903937"
    },
    {
        "DATE": "2020/12/22",
        "city": "xin_jiang",
        "max": "13.060182",
        "min": "-1.4745646"
    },
    {
        "DATE": "2020/12/23",
        "city": "xin_jiang",
        "max": "10.939157",
        "min": "-1.3760955"
    },
    {
        "DATE": "2020/12/24",
        "city": "xin_jiang",
        "max": "7.1939898",
        "min": "-5.80457"
    },
    {
        "DATE": "2020/12/25",
        "city": "xin_jiang",
        "max": "12.067299",
        "min": "-0.8033577"
    },
    {
        "DATE": "2020/12/26",
        "city": "xin_jiang",
        "max": "13.493795",
        "min": "1.1910098"
    },
    {
        "DATE": "2020/12/27",
        "city": "xin_jiang",
        "max": "20.030642",
        "min": "5.5402336"
    },
    {
        "DATE": "2020/12/28",
        "city": "xin_jiang",
        "max": "26.230791",
        "min": "4.3321733"
    },
    {
        "DATE": "2020/12/29",
        "city": "xin_jiang",
        "max": "24.494484",
        "min": "8.142178"
    },
    {
        "DATE": "2020/12/30",
        "city": "xin_jiang",
        "max": "24.991297",
        "min": "5.798851"
    },
    {
        "DATE": "2020/12/31",
        "city": "xin_jiang",
        "max": "24.528921",
        "min": "9.403397"
    }
]